CHANGELOG.txt
MANIFEST.in
README.rst
setup.py
src/geoffrey/__init__.py
src/geoffrey/__meta__.py
src/geoffrey/data.py
src/geoffrey/defaults.py
src/geoffrey/hub.py
src/geoffrey/main.py
src/geoffrey/plugin.py
src/geoffrey/project.py
src/geoffrey/server.py
src/geoffrey/subscription.py
src/geoffrey/utils.py
src/geoffrey/webserver.py
src/geoffrey/websocket.py
src/geoffrey.egg-info/PKG-INFO
src/geoffrey.egg-info/SOURCES.txt
src/geoffrey.egg-info/dependency_links.txt
src/geoffrey.egg-info/entry_points.txt
src/geoffrey.egg-info/requires.txt
src/geoffrey.egg-info/top_level.txt
src/geoffrey/deps/__init__.py
src/geoffrey/deps/aiobottle/README.md
src/geoffrey/deps/aiobottle/__init__.py
src/geoffrey/deps/straight/AUTHORS
src/geoffrey/deps/straight/LICENSE
src/geoffrey/deps/straight/README.rst
src/geoffrey/deps/straight/__init__.py
src/geoffrey/deps/straight/plugin/__init__.py
src/geoffrey/deps/straight/plugin/loaders.py
src/geoffrey/deps/straight/plugin/manager.py
src/geoffrey/web/index.html
src/geoffrey/web/project.html
src/geoffrey/web/assets/geoffrey.jpg
src/geoffrey/web/assets/css/AdminLTE.css
src/geoffrey/web/assets/css/dataTables.bootstrap.css
src/geoffrey/web/assets/css/font-awesome.css
src/geoffrey/web/assets/css/font-awesome.min.css
src/geoffrey/web/assets/css/geoffrey.css
src/geoffrey/web/assets/css/ionicons.css
src/geoffrey/web/assets/css/ionicons.min.css
src/geoffrey/web/assets/css/images/animated-overlay.gif
src/geoffrey/web/assets/css/images/sort_asc.png
src/geoffrey/web/assets/css/images/sort_both.png
src/geoffrey/web/assets/css/images/sort_desc.png
src/geoffrey/web/assets/css/images/ui-bg_flat_0_aaaaaa_40x100.png
src/geoffrey/web/assets/css/images/ui-bg_flat_55_fbec88_40x100.png
src/geoffrey/web/assets/css/images/ui-bg_glass_75_d0e5f5_1x400.png
src/geoffrey/web/assets/css/images/ui-bg_glass_85_dfeffc_1x400.png
src/geoffrey/web/assets/css/images/ui-bg_glass_95_fef1ec_1x400.png
src/geoffrey/web/assets/css/images/ui-bg_gloss-wave_55_5c9ccc_500x100.png
src/geoffrey/web/assets/css/images/ui-bg_inset-hard_100_f5f8f9_1x100.png
src/geoffrey/web/assets/css/images/ui-bg_inset-hard_100_fcfdfd_1x100.png
src/geoffrey/web/assets/css/images/ui-icons_217bc0_256x240.png
