Metadata-Version: 1.0
Name: geoffrey
Version: 0.1.0
Summary: Geoffrey: Real Time Continuous Integration Server
Home-page: https://github.com/nilp0inter/geoffrey
Author: Roberto Abdelkader Martínez Pérez
Author-email: robertomartinezp@gmail.com
License: LGPLv3
Keywords: geoffrey continuous integration server
Platform: UNKNOWN
